jsondb_in_memory.cp310-win_amd64.pyd
jsondb_in_memory/Exceptions.py
jsondb_in_memory/__init__.py
jsondb_in_memory/jsondb_in_memory.py
jsondb_in_memory-0.0.8.dist-info/LICENSE
jsondb_in_memory-0.0.8.dist-info/METADATA
jsondb_in_memory-0.0.8.dist-info/WHEEL
jsondb_in_memory-0.0.8.dist-info/top_level.txt
jsondb_in_memory-0.0.8.dist-info/RECORD
